ali_tool/__init__.py
ali_tool/cli.py
ali_tool/core/__init__.py
ali_tool/core/logging.py
ali_tool/core/plugin.py
ali_tool/core/registry.py
ali_tool/core/resolver.py
ali_tool/core/router.py
ali_tool/plugins/broot/ali.hjson
ali_tool/plugins/broot/plugin.yaml
ali_tool/plugins/llms.txt
ali_tool/plugins/micro/plugin.yaml
ali_tool/plugins/tmux/plugin.yaml
ali_tool/plugins/tmux/scripts/distribute.py
ali_tool/plugins/tmux/tmux.conf.ali
ali_tool/scripts.py
ali_tool-0.1.1.dist-info/WHEEL
ali_tool-0.1.1.dist-info/entry_points.txt
ali_tool-0.1.1.dist-info/METADATA
ali_tool-0.1.1.dist-info/RECORD
