Metadata-Version: 2.3
Name: ali-tool
Version: 0.1.1
Summary: Action Language Interpreter - One command for every tool
Author: Fredrik Angelsen
Author-email: Fredrik Angelsen <fredrikangelsen@gmail.com>
Requires-Dist: pyyaml>=6.0.2
Requires-Python: >=3.12
